Metadata-Version: 2.1
Name: pytictacbot
Version: 1.6
Summary: A program that makes you unbeatable at BombParty
